metabasic/__init__.py
metabasic/exceptions.py
metabasic/metabasic.py
metabasic/py.typed
metabasic-0.5.1.dist-info/LICENSE
metabasic-0.5.1.dist-info/WHEEL
metabasic-0.5.1.dist-info/METADATA
metabasic-0.5.1.dist-info/RECORD
