Metadata-Version: 2.1
Name: metabasic
Version: 0.5.1
Summary: Dead simple client for interacting with the Metabase dataset API
Home-page: https://github.com/Ben-Hu/metabasic
License: MIT
Author: Ben-Hu
Author-email: benjqh@gmail.com
Requires-Python: >=3.6.1
Classifier: License :: OSI Approved :: MIT License
Classifier: Programming Language :: Python :: 3
Classifier: Programming Language :: Python :: 3.7
Classifier: Programming Language :: Python :: 3.8
Classifier: Programming Language :: Python :: 3.9
Requires-Dist: inquirer (>=2.6.3,<3.0.0)
Requires-Dist: pandas (>=1.0.3,<2.0.0)
Requires-Dist: requests (>=2.22.0,<3.0.0)
Project-URL: Documentation, https://ben-hu.com/metabasic
Project-URL: Repository, https://github.com/Ben-Hu/metabasic
